MANIFEST.in
README.md
setup.py
jiayan/__init__.py
jiayan/__main__.py
jiayan/examples.py
jiayan/globals.py
jiayan/linguistic_unit.py
jiayan/test.py
jiayan/utils.py
jiayan.egg-info/PKG-INFO
jiayan.egg-info/SOURCES.txt
jiayan.egg-info/dependency_links.txt
jiayan.egg-info/requires.txt
jiayan.egg-info/top_level.txt
jiayan/data/__init__.py
jiayan/data/char_pos_dict.json
jiayan/data/dict.txt
jiayan/lexicon/__init__.py
jiayan/lexicon/pmi_entropy_constructor.py
jiayan/postagger/__init__.py
jiayan/postagger/crf_pos_tagger.py
jiayan/sentencizer/__init__.py
jiayan/sentencizer/crf_punctuator.py
jiayan/sentencizer/crf_sent_tagger.py
jiayan/sentencizer/crf_sentencizer.py
jiayan/tokenizer/__init__.py
jiayan/tokenizer/hmm_tokenizer.py
jiayan/tokenizer/ngram_tokenizer.py
jiayan/translator/__init__.py