Metadata-Version: 2.1
Name: jiayan
Version: 0.0.21
Summary: The NLP toolkit designed for classical chinese.
Home-page: https://github.com/jiaeyan/Jiayan
Author: Jiajie Yan
Author-email: jiaeyan@gmail.com
License: MIT
Keywords: classical-chinese,ancient-chinese,nlp
Platform: UNKNOWN
Classifier: Programming Language :: Python
Classifier: Programming Language :: Python :: 2
Classifier: Programming Language :: Python :: 2.6
Classifier: Programming Language :: Python :: 2.7
Classifier: Programming Language :: Python :: 3
Classifier: Programming Language :: Python :: 3.3
Classifier: Programming Language :: Python :: 3.4
Classifier: Programming Language :: Python :: 3.5
Classifier: Programming Language :: Python :: 3.6
Classifier: Topic :: Utilities
Classifier: Topic :: Text Processing
Requires-Python: >=2.6, >=3
